odoo/addons/res_config_settings_enterprise_remove/README.rst
odoo/addons/res_config_settings_enterprise_remove/__init__.py
odoo/addons/res_config_settings_enterprise_remove/__manifest__.py
odoo/addons/res_config_settings_enterprise_remove/i18n/de.po
odoo/addons/res_config_settings_enterprise_remove/i18n/es.po
odoo/addons/res_config_settings_enterprise_remove/i18n/it.po
odoo/addons/res_config_settings_enterprise_remove/i18n/nl_NL.po
odoo/addons/res_config_settings_enterprise_remove/models/__init__.py
odoo/addons/res_config_settings_enterprise_remove/models/res_config_settings.py
odoo/addons/res_config_settings_enterprise_remove/static/description/icon.png
odoo11_addon_res_config_settings_enterprise_remove-11.0.1.0.0.dist-info/DESCRIPTION.rst
odoo11_addon_res_config_settings_enterprise_remove-11.0.1.0.0.dist-info/METADATA
odoo11_addon_res_config_settings_enterprise_remove-11.0.1.0.0.dist-info/RECORD
odoo11_addon_res_config_settings_enterprise_remove-11.0.1.0.0.dist-info/WHEEL
odoo11_addon_res_config_settings_enterprise_remove-11.0.1.0.0.dist-info/metadata.json
odoo11_addon_res_config_settings_enterprise_remove-11.0.1.0.0.dist-info/top_level.txt
